<?xml version="1.0" encoding="UTF-8"?>
<MetaDataObject xmlns="http://v8.1c.ru/8.3/MDClasses" xmlns:app="http://v8.1c.ru/8.2/managed-application/core" xmlns:cfg="http://v8.1c.ru/8.1/data/enterprise/current-config" xmlns:cmi="http://v8.1c.ru/8.2/managed-application/cmi" xmlns:ent="http://v8.1c.ru/8.1/data/enterprise" xmlns:lf="http://v8.1c.ru/8.2/managed-application/logform" xmlns:style="http://v8.1c.ru/8.1/data/ui/style" xmlns:sys="http://v8.1c.ru/8.1/data/ui/fonts/system" xmlns:v8="http://v8.1c.ru/8.1/data/core" xmlns:v8ui="http://v8.1c.ru/8.1/data/ui" xmlns:web="http://v8.1c.ru/8.1/data/ui/colors/web" xmlns:win="http://v8.1c.ru/8.1/data/ui/colors/windows" xmlns:xen="http://v8.1c.ru/8.3/xcf/enums" xmlns:xpr="http://v8.1c.ru/8.3/xcf/predef" xmlns:xr="http://v8.1c.ru/8.3/xcf/readable" xmlns:xs="http://www.w3.org/2001/XMLSchema" xmlns:xsi="http://www.w3.org/2001/XMLSchema-instance" version="2.11">
	<DocumentJournal uuid="416c9a24-074d-4c06-ad0d-14cbc80ae552">
		<InternalInfo>
			<xr:GeneratedType name="DocumentJournalSelection.ДокументыПоЭСФ" category="Selection">
				<xr:TypeId>8c3d56cd-817a-4e9e-83a3-f50397019802</xr:TypeId>
				<xr:ValueId>64660e9c-f96c-454f-adc4-0838ccc00dc1</xr:ValueId>
			</xr:GeneratedType>
			<xr:GeneratedType name="DocumentJournalList.ДокументыПоЭСФ" category="List">
				<xr:TypeId>ad651e5f-4961-4365-a9df-2d90503cc18c</xr:TypeId>
				<xr:ValueId>7bd373c4-9635-40c9-a9e0-d988b5ec9325</xr:ValueId>
			</xr:GeneratedType>
			<xr:GeneratedType name="DocumentJournalManager.ДокументыПоЭСФ" category="Manager">
				<xr:TypeId>5e4ff2b8-74f1-499e-af32-538ccfb57218</xr:TypeId>
				<xr:ValueId>6865547c-0cf2-45ec-a21b-7be1a9dcd1e9</xr:ValueId>
			</xr:GeneratedType>
		</InternalInfo>
		<Properties>
			<Name>ДокументыПоЭСФ</Name>
			<Synonym>
				<v8:item>
					<v8:lang>ru</v8:lang>
					<v8:content>Документы по ЭСФ</v8:content>
				</v8:item>
			</Synonym>
			<Comment/>
			<DefaultForm>DocumentJournal.ДокументыПоЭСФ.Form.ФормаСписка</DefaultForm>
			<AuxiliaryForm/>
			<UseStandardCommands>false</UseStandardCommands>
			<RegisteredDocuments>
				<xr:Item xsi:type="xr:MDObjectRef">Document.ЭлектронныйСчетФактураВыписанный</xr:Item>
				<xr:Item xsi:type="xr:MDObjectRef">Document.ЭлектронныйСчетФактураПолученный</xr:Item>
			</RegisteredDocuments>
			<IncludeHelpInContents>true</IncludeHelpInContents>
			<StandardAttributes>
				<xr:StandardAttribute name="Type">
					<xr:LinkByType/>
					<xr:FillChecking>DontCheck</xr:FillChecking>
					<xr:MultiLine>false</xr:MultiLine>
					<xr:FillFromFillingValue>false</xr:FillFromFillingValue>
					<xr:CreateOnInput>Auto</xr:CreateOnInput>
					<xr:MaxValue xsi:nil="true"/>
					<xr:ToolTip>
						<v8:item>
							<v8:lang>ru</v8:lang>
							<v8:content>Тип документа</v8:content>
						</v8:item>
					</xr:ToolTip>
					<xr:ExtendedEdit>false</xr:ExtendedEdit>
					<xr:Format/>
					<xr:ChoiceForm/>
					<xr:QuickChoice>Auto</xr:QuickChoice>
					<xr:ChoiceHistoryOnInput>Auto</xr:ChoiceHistoryOnInput>
					<xr:EditFormat/>
					<xr:PasswordMode>false</xr:PasswordMode>
					<xr:DataHistory>Use</xr:DataHistory>
					<xr:MarkNegatives>false</xr:MarkNegatives>
					<xr:MinValue xsi:nil="true"/>
					<xr:Synonym>
						<v8:item>
							<v8:lang>ru</v8:lang>
							<v8:content>Тип</v8:content>
						</v8:item>
					</xr:Synonym>
					<xr:Comment/>
					<xr:FullTextSearch>Use</xr:FullTextSearch>
					<xr:ChoiceParameterLinks/>
					<xr:FillValue xsi:nil="true"/>
					<xr:Mask/>
					<xr:ChoiceParameters/>
				</xr:StandardAttribute>
				<xr:StandardAttribute name="Ref">
					<xr:LinkByType/>
					<xr:FillChecking>DontCheck</xr:FillChecking>
					<xr:MultiLine>false</xr:MultiLine>
					<xr:FillFromFillingValue>false</xr:FillFromFillingValue>
					<xr:CreateOnInput>Auto</xr:CreateOnInput>
					<xr:MaxValue xsi:nil="true"/>
					<xr:ToolTip>
						<v8:item>
							<v8:lang>ru</v8:lang>
							<v8:content>Ссылка на документ</v8:content>
						</v8:item>
					</xr:ToolTip>
					<xr:ExtendedEdit>false</xr:ExtendedEdit>
					<xr:Format/>
					<xr:ChoiceForm/>
					<xr:QuickChoice>Auto</xr:QuickChoice>
					<xr:ChoiceHistoryOnInput>Auto</xr:ChoiceHistoryOnInput>
					<xr:EditFormat/>
					<xr:PasswordMode>false</xr:PasswordMode>
					<xr:DataHistory>Use</xr:DataHistory>
					<xr:MarkNegatives>false</xr:MarkNegatives>
					<xr:MinValue xsi:nil="true"/>
					<xr:Synonym>
						<v8:item>
							<v8:lang>ru</v8:lang>
							<v8:content>Ссылка</v8:content>
						</v8:item>
					</xr:Synonym>
					<xr:Comment/>
					<xr:FullTextSearch>Use</xr:FullTextSearch>
					<xr:ChoiceParameterLinks/>
					<xr:FillValue xsi:nil="true"/>
					<xr:Mask/>
					<xr:ChoiceParameters/>
				</xr:StandardAttribute>
				<xr:StandardAttribute name="Date">
					<xr:LinkByType/>
					<xr:FillChecking>DontCheck</xr:FillChecking>
					<xr:MultiLine>false</xr:MultiLine>
					<xr:FillFromFillingValue>false</xr:FillFromFillingValue>
					<xr:CreateOnInput>Auto</xr:CreateOnInput>
					<xr:MaxValue xsi:nil="true"/>
					<xr:ToolTip>
						<v8:item>
							<v8:lang>ru</v8:lang>
							<v8:content>Дата документа</v8:content>
						</v8:item>
					</xr:ToolTip>
					<xr:ExtendedEdit>false</xr:ExtendedEdit>
					<xr:Format/>
					<xr:ChoiceForm/>
					<xr:QuickChoice>Auto</xr:QuickChoice>
					<xr:ChoiceHistoryOnInput>Auto</xr:ChoiceHistoryOnInput>
					<xr:EditFormat/>
					<xr:PasswordMode>false</xr:PasswordMode>
					<xr:DataHistory>Use</xr:DataHistory>
					<xr:MarkNegatives>false</xr:MarkNegatives>
					<xr:MinValue xsi:nil="true"/>
					<xr:Synonym>
						<v8:item>
							<v8:lang>ru</v8:lang>
							<v8:content>Дата</v8:content>
						</v8:item>
					</xr:Synonym>
					<xr:Comment/>
					<xr:FullTextSearch>Use</xr:FullTextSearch>
					<xr:ChoiceParameterLinks/>
					<xr:FillValue xsi:nil="true"/>
					<xr:Mask/>
					<xr:ChoiceParameters/>
				</xr:StandardAttribute>
				<xr:StandardAttribute name="Posted">
					<xr:LinkByType/>
					<xr:FillChecking>DontCheck</xr:FillChecking>
					<xr:MultiLine>false</xr:MultiLine>
					<xr:FillFromFillingValue>false</xr:FillFromFillingValue>
					<xr:CreateOnInput>Auto</xr:CreateOnInput>
					<xr:MaxValue xsi:nil="true"/>
					<xr:ToolTip>
						<v8:item>
							<v8:lang>ru</v8:lang>
							<v8:content>Признак проведения документа</v8:content>
						</v8:item>
					</xr:ToolTip>
					<xr:ExtendedEdit>false</xr:ExtendedEdit>
					<xr:Format/>
					<xr:ChoiceForm/>
					<xr:QuickChoice>Auto</xr:QuickChoice>
					<xr:ChoiceHistoryOnInput>Auto</xr:ChoiceHistoryOnInput>
					<xr:EditFormat/>
					<xr:PasswordMode>false</xr:PasswordMode>
					<xr:DataHistory>Use</xr:DataHistory>
					<xr:MarkNegatives>false</xr:MarkNegatives>
					<xr:MinValue xsi:nil="true"/>
					<xr:Synonym>
						<v8:item>
							<v8:lang>ru</v8:lang>
							<v8:content>Проведен</v8:content>
						</v8:item>
					</xr:Synonym>
					<xr:Comment/>
					<xr:FullTextSearch>Use</xr:FullTextSearch>
					<xr:ChoiceParameterLinks/>
					<xr:FillValue xsi:nil="true"/>
					<xr:Mask/>
					<xr:ChoiceParameters/>
				</xr:StandardAttribute>
				<xr:StandardAttribute name="DeletionMark">
					<xr:LinkByType/>
					<xr:FillChecking>DontCheck</xr:FillChecking>
					<xr:MultiLine>false</xr:MultiLine>
					<xr:FillFromFillingValue>false</xr:FillFromFillingValue>
					<xr:CreateOnInput>Auto</xr:CreateOnInput>
					<xr:MaxValue xsi:nil="true"/>
					<xr:ToolTip>
						<v8:item>
							<v8:lang>ru</v8:lang>
							<v8:content>Пометка удаления документа</v8:content>
						</v8:item>
					</xr:ToolTip>
					<xr:ExtendedEdit>false</xr:ExtendedEdit>
					<xr:Format/>
					<xr:ChoiceForm/>
					<xr:QuickChoice>Auto</xr:QuickChoice>
					<xr:ChoiceHistoryOnInput>Auto</xr:ChoiceHistoryOnInput>
					<xr:EditFormat/>
					<xr:PasswordMode>false</xr:PasswordMode>
					<xr:DataHistory>Use</xr:DataHistory>
					<xr:MarkNegatives>false</xr:MarkNegatives>
					<xr:MinValue xsi:nil="true"/>
					<xr:Synonym/>
					<xr:Comment>Пометка удаления</xr:Comment>
					<xr:FullTextSearch>Use</xr:FullTextSearch>
					<xr:ChoiceParameterLinks/>
					<xr:FillValue xsi:nil="true"/>
					<xr:Mask/>
					<xr:ChoiceParameters/>
				</xr:StandardAttribute>
				<xr:StandardAttribute name="Number">
					<xr:LinkByType/>
					<xr:FillChecking>DontCheck</xr:FillChecking>
					<xr:MultiLine>false</xr:MultiLine>
					<xr:FillFromFillingValue>false</xr:FillFromFillingValue>
					<xr:CreateOnInput>Auto</xr:CreateOnInput>
					<xr:MaxValue xsi:nil="true"/>
					<xr:ToolTip>
						<v8:item>
							<v8:lang>ru</v8:lang>
							<v8:content>Номер документа</v8:content>
						</v8:item>
					</xr:ToolTip>
					<xr:ExtendedEdit>false</xr:ExtendedEdit>
					<xr:Format/>
					<xr:ChoiceForm/>
					<xr:QuickChoice>Auto</xr:QuickChoice>
					<xr:ChoiceHistoryOnInput>Auto</xr:ChoiceHistoryOnInput>
					<xr:EditFormat/>
					<xr:PasswordMode>false</xr:PasswordMode>
					<xr:DataHistory>Use</xr:DataHistory>
					<xr:MarkNegatives>false</xr:MarkNegatives>
					<xr:MinValue xsi:nil="true"/>
					<xr:Synonym>
						<v8:item>
							<v8:lang>ru</v8:lang>
							<v8:content>Номер</v8:content>
						</v8:item>
					</xr:Synonym>
					<xr:Comment/>
					<xr:FullTextSearch>Use</xr:FullTextSearch>
					<xr:ChoiceParameterLinks/>
					<xr:FillValue xsi:nil="true"/>
					<xr:Mask/>
					<xr:ChoiceParameters/>
				</xr:StandardAttribute>
			</StandardAttributes>
			<ListPresentation/>
			<ExtendedListPresentation/>
			<Explanation/>
		</Properties>
		<ChildObjects>
			<Column uuid="d087e90a-bb66-4fec-8d8a-3fdf21ee2811">
				<Properties>
					<Name>Организация</Name>
					<Synonym>
						<v8:item>
							<v8:lang>ru</v8:lang>
							<v8:content>Организация</v8:content>
						</v8:item>
					</Synonym>
					<Comment/>
					<Indexing>DontIndex</Indexing>
					<References>
						<xr:Item xsi:type="xr:MDObjectRef">Document.ЭлектронныйСчетФактураВыписанный.Attribute.Организация</xr:Item>
						<xr:Item xsi:type="xr:MDObjectRef">Document.ЭлектронныйСчетФактураПолученный.Attribute.Организация</xr:Item>
					</References>
				</Properties>
			</Column>
			<Column uuid="3f01de3e-3199-4d8a-a59a-f10c7843d5c8">
				<Properties>
					<Name>ВидОперации</Name>
					<Synonym>
						<v8:item>
							<v8:lang>ru</v8:lang>
							<v8:content>Вид операции</v8:content>
						</v8:item>
					</Synonym>
					<Comment/>
					<Indexing>DontIndex</Indexing>
					<References>
						<xr:Item xsi:type="xr:MDObjectRef">Document.ЭлектронныйСчетФактураВыписанный.Attribute.ВидОперации</xr:Item>
						<xr:Item xsi:type="xr:MDObjectRef">Document.ЭлектронныйСчетФактураПолученный.Attribute.ВидОперации</xr:Item>
					</References>
				</Properties>
			</Column>
			<Column uuid="50849b73-e952-46bd-9c21-79a4bb1c8a81">
				<Properties>
					<Name>Контрагент</Name>
					<Synonym>
						<v8:item>
							<v8:lang>ru</v8:lang>
							<v8:content>Контрагент</v8:content>
						</v8:item>
					</Synonym>
					<Comment/>
					<Indexing>DontIndex</Indexing>
					<References>
						<xr:Item xsi:type="xr:MDObjectRef">Document.ЭлектронныйСчетФактураВыписанный.Attribute.Контрагент</xr:Item>
						<xr:Item xsi:type="xr:MDObjectRef">Document.ЭлектронныйСчетФактураПолученный.Attribute.Контрагент</xr:Item>
					</References>
				</Properties>
			</Column>
			<Column uuid="6bb4695f-21d6-4ba5-b667-bccba0678881">
				<Properties>
					<Name>ДоговорКонтрагента</Name>
					<Synonym>
						<v8:item>
							<v8:lang>ru</v8:lang>
							<v8:content>Договор контрагента</v8:content>
						</v8:item>
					</Synonym>
					<Comment/>
					<Indexing>DontIndex</Indexing>
					<References>
						<xr:Item xsi:type="xr:MDObjectRef">Document.ЭлектронныйСчетФактураВыписанный.Attribute.ДоговорКонтрагента</xr:Item>
						<xr:Item xsi:type="xr:MDObjectRef">Document.ЭлектронныйСчетФактураПолученный.Attribute.ДоговорКонтрагента</xr:Item>
					</References>
				</Properties>
			</Column>
			<Column uuid="8d84c2d1-c553-43aa-8d73-bd5c2f1fe7d7">
				<Properties>
					<Name>НомерЭСФ</Name>
					<Synonym>
						<v8:item>
							<v8:lang>ru</v8:lang>
							<v8:content>Номер ЭСФ</v8:content>
						</v8:item>
					</Synonym>
					<Comment/>
					<Indexing>DontIndex</Indexing>
					<References>
						<xr:Item xsi:type="xr:MDObjectRef">Document.ЭлектронныйСчетФактураВыписанный.Attribute.НомерЭСФ</xr:Item>
						<xr:Item xsi:type="xr:MDObjectRef">Document.ЭлектронныйСчетФактураПолученный.Attribute.НомерЭСФ</xr:Item>
					</References>
				</Properties>
			</Column>
			<Column uuid="b9b4a85b-781d-4107-8a8a-952f85bbf71b">
				<Properties>
					<Name>СуммаДокумента</Name>
					<Synonym>
						<v8:item>
							<v8:lang>ru</v8:lang>
							<v8:content>Сумма</v8:content>
						</v8:item>
					</Synonym>
					<Comment/>
					<Indexing>DontIndex</Indexing>
					<References>
						<xr:Item xsi:type="xr:MDObjectRef">Document.ЭлектронныйСчетФактураВыписанный.Attribute.СуммаДокумента</xr:Item>
						<xr:Item xsi:type="xr:MDObjectRef">Document.ЭлектронныйСчетФактураПолученный.Attribute.СуммаДокумента</xr:Item>
					</References>
				</Properties>
			</Column>
			<Column uuid="9938a46f-6f42-44ef-8bab-ecafbd4e89d9">
				<Properties>
					<Name>Валюта</Name>
					<Synonym>
						<v8:item>
							<v8:lang>ru</v8:lang>
							<v8:content>Валюта</v8:content>
						</v8:item>
					</Synonym>
					<Comment/>
					<Indexing>DontIndex</Indexing>
					<References>
						<xr:Item xsi:type="xr:MDObjectRef">Document.ЭлектронныйСчетФактураВыписанный.Attribute.ВалютаДокумента</xr:Item>
						<xr:Item xsi:type="xr:MDObjectRef">Document.ЭлектронныйСчетФактураПолученный.Attribute.ВалютаДокумента</xr:Item>
					</References>
				</Properties>
			</Column>
			<Column uuid="f7779133-fab4-4c92-9dc6-d79517129450">
				<Properties>
					<Name>Комментарий</Name>
					<Synonym>
						<v8:item>
							<v8:lang>ru</v8:lang>
							<v8:content>Комментарий</v8:content>
						</v8:item>
					</Synonym>
					<Comment/>
					<Indexing>DontIndex</Indexing>
					<References>
						<xr:Item xsi:type="xr:MDObjectRef">Document.ЭлектронныйСчетФактураВыписанный.Attribute.Комментарий</xr:Item>
						<xr:Item xsi:type="xr:MDObjectRef">Document.ЭлектронныйСчетФактураПолученный.Attribute.Комментарий</xr:Item>
					</References>
				</Properties>
			</Column>
			<Column uuid="0a6e62fe-a4a9-408e-b26c-693e9586d142">
				<Properties>
					<Name>Автор</Name>
					<Synonym>
						<v8:item>
							<v8:lang>ru</v8:lang>
							<v8:content>Автор</v8:content>
						</v8:item>
					</Synonym>
					<Comment/>
					<Indexing>DontIndex</Indexing>
					<References>
						<xr:Item xsi:type="xr:MDObjectRef">Document.ЭлектронныйСчетФактураВыписанный.Attribute.Автор</xr:Item>
						<xr:Item xsi:type="xr:MDObjectRef">Document.ЭлектронныйСчетФактураПолученный.Attribute.Автор</xr:Item>
					</References>
				</Properties>
			</Column>
			<Form>ФормаСписка</Form>
			<Command uuid="54aea482-dafc-42e7-a590-9c3c6c020d57">
				<Properties>
					<Name>ДокументыПоЭСФ</Name>
					<Synonym>
						<v8:item>
							<v8:lang>ru</v8:lang>
							<v8:content>Документы по ЭСФ</v8:content>
						</v8:item>
					</Synonym>
					<Comment/>
					<Group>NavigationPanelOrdinary</Group>
					<CommandParameterType/>
					<ParameterUseMode>Single</ParameterUseMode>
					<ModifiesData>false</ModifiesData>
					<Representation>Auto</Representation>
					<ToolTip/>
					<Picture/>
					<Shortcut/>
					<OnMainServerUnavalableBehavior>Auto</OnMainServerUnavalableBehavior>
				</Properties>
			</Command>
		</ChildObjects>
	</DocumentJournal>
</MetaDataObject>